{"version":1,"resource":"file:///home/gsmith-alvarez/dotfiles/README.md","entries":[{"id":"PNlU.md","timestamp":1771841293228},{"id":"CjaL.md","timestamp":1771841567854},{"id":"G3hS.md","timestamp":1771841663314},{"id":"rN9P.md","timestamp":1771841895111},{"id":"ngXT.md","timestamp":1771841931665},{"id":"oCZ5.md","timestamp":1771910090921},{"id":"OLCn.md","timestamp":1771910247370},{"id":"MxTA.md","timestamp":1771910347378},{"id":"tFFn.md","timestamp":1771910434457},{"id":"CeK5.md","timestamp":1771910445922},{"id":"dFLo.md","timestamp":1771986890468}]}